ductile/__init__.py
ductile/py.typed
ductile/state.py
ductile/view.py
ductile/controller/__init__.py
ductile/controller/controller.py
ductile/controller/interaction_controller.py
ductile/controller/messageable_controller.py
ductile/controller/type.py
ductile/internal/__init__.py
ductile/internal/view.py
ductile/pagination/__init__.py
ductile/pagination/page.py
ductile/types/__init__.py
ductile/types/callback.py
ductile/types/view.py
ductile/ui/__init__.py
ductile/ui/button.py
ductile/ui/modal.py
ductile/ui/select.py
ductile/utils/__init__.py
ductile/utils/async_helper.py
ductile/utils/call.py
ductile/utils/chunk.py
ductile/utils/debounce.py
ductile/utils/logger.py
ductile/utils/type_helper.py
ductile_ui-0.4.0.dist-info/METADATA
ductile_ui-0.4.0.dist-info/WHEEL
ductile_ui-0.4.0.dist-info/licenses/LICENSE
ductile_ui-0.4.0.dist-info/RECORD
