Metadata-Version: 2.3
Name: ductile-ui
Version: 0.4.0
Summary: A library provides declarative ui for discord.py
Project-URL: Repository, https://github.com/sushi-chaaaan/ductile-ui
Project-URL: Issues, https://github.com/sushi-chaaaan/ductile-ui/issues
Author-email: sushichan044 <mail@sushichan.live>
License: MIT License
License-File: LICENSE
Keywords: discord,discord.py,ductile,ductile-ui
Classifier: Development Status :: 3 - Alpha
Classifier: Intended Audience :: Developers
Classifier: License :: OSI Approved :: MIT License
Classifier: Natural Language :: English
Classifier: Operating System :: OS Independent
Classifier: Programming Language :: Python :: 3.10
Classifier: Programming Language :: Python :: 3.11
Classifier: Topic :: Internet
Classifier: Topic :: Software Development :: Libraries
Classifier: Topic :: Software Development :: Libraries :: Python Modules
Classifier: Topic :: Utilities
Classifier: Typing :: Typed
Requires-Python: >=3.10
Requires-Dist: discord-py>=2.2.0
Requires-Dist: pydantic>=2.9.2
Requires-Dist: typing-extensions>=4.12.2
